wav2polaris/__init__.py
wav2polaris/__main__.py
wav2polaris/sound.py
wav2polaris/utils.py
wav2polaris/wav2polaris.py
wav2polaris-0.4.1.dist-info/licenses/COPYING
wav2polaris-0.4.1.dist-info/licenses/LICENSE
wav2polaris-0.4.1.dist-info/METADATA
wav2polaris-0.4.1.dist-info/WHEEL
wav2polaris-0.4.1.dist-info/entry_points.txt
wav2polaris-0.4.1.dist-info/top_level.txt
wav2polaris-0.4.1.dist-info/RECORD
