Metadata-Version: 2.4
Name: wav2polaris
Version: 0.4.1
Summary: Python program for converting lightsaber sound font .wav files to .RAW files for Polaris Anima sabers
Author-email: Jason Ramboz <jramboz@gmail.com>
License:                     GNU GENERAL PUBLIC LICENSE
Project-URL: Homepage, https://github.com/jramboz/wav2polaris
Keywords: polaris,ludosport,lightsabers,opencore
Classifier: License :: OSI Approved :: GNU General Public License v3 (GPLv3)
Classifier: Programming Language :: Python
Classifier: Programming Language :: Python :: 3
Classifier: Development Status :: 4 - Beta
Requires-Python: >=3.9
License-File: LICENSE
License-File: COPYING
Requires-Dist: py-getch>=1.0.1
Requires-Dist: pydub>=0.25.1
Requires-Dist: audioop-lts>=0.2.1
Dynamic: license-file
